fitbark/__init__.py
fitbark/api.py
fitbark/exceptions.py
fitbark/utils.py
fitbark-0.0.1.dist-info/AUTHORS
fitbark-0.0.1.dist-info/LICENSE
fitbark-0.0.1.dist-info/METADATA
fitbark-0.0.1.dist-info/WHEEL
fitbark-0.0.1.dist-info/top_level.txt
fitbark-0.0.1.dist-info/RECORD
