Metadata-Version: 2.1
Name: fitbark
Version: 0.0.1
Summary: FitBark API Wrapper.
Home-page: https://github.com/alexhouse/python-fitbark
Author: Alex House
Author-email: house.alexander@gmail.com
License: Apache 2.0
Platform: UNKNOWN
Classifier: Intended Audience :: Developers
Classifier: Natural Language :: English
Classifier: License :: OSI Approved :: Apache Software License
Classifier: Programming Language :: Python
Classifier: Programming Language :: Python :: 2.7
Classifier: Programming Language :: Python :: 3
Classifier: Programming Language :: Python :: 3.4
Classifier: Programming Language :: Python :: 3.5
Classifier: Programming Language :: Python :: 3.6
Classifier: Programming Language :: Python :: Implementation :: PyPy
Requires-Dist: setuptools
Requires-Dist: python-dateutil (>=1.5)
Requires-Dist: requests-oauthlib (>=0.7)
